{
  "commands": [
    {
      "id": 1,
      "name": "STOP",
      "description": "Emergency stop - halt all motors immediately",
      "params": []
    },
    {
      "id": 2,
      "name": "MOVE",
      "description": "Move the robot by a given distance",
      "params": [
        {
          "name": "distance",
          "type": "FLOAT",
          "required": false,
          "description": "Distance to move in meters"
        }
      ]
    },
    {
      "id": 4,
      "name": "ROTATE",
      "description": "Rotate the robot by a given angle",
      "params": [
        {
          "name": "angle",
          "type": "FLOAT",
          "required": true,
          "description": "Rotation angle in degrees"
        }
      ]
    }
  ]
}